py3cw/__init__.py
py3cw/config.py
py3cw/request.py
py3cw/test_request.py
py3cw/utils.py
py3cw_am11yfork-0.0.18.dist-info/LICENSE
py3cw_am11yfork-0.0.18.dist-info/METADATA
py3cw_am11yfork-0.0.18.dist-info/WHEEL
py3cw_am11yfork-0.0.18.dist-info/top_level.txt
py3cw_am11yfork-0.0.18.dist-info/RECORD
