Metadata-Version: 2.1
Name: py3cw-am11yfork
Version: 0.0.18
Summary: 3commas Python wrapper
Home-page: https://github.com/am11y/py3cw-am11yfork
Author: Bogdan Teodoru
Author-email: me@bogdanteodoru.com
License: MIT
Keywords: api 3commas trading crypto bitcoin altcoin
Platform: UNKNOWN
Classifier: Development Status :: 5 - Production/Stable
Requires-Dist: requests
